aiida_defects/__init__.py
aiida_defects/utils.py
aiida_defects/data/data.py
aiida_defects/formation_energy/__init__.py
aiida_defects/formation_energy/defect_chemistry_base.py
aiida_defects/formation_energy/defect_chemistry_qe.py
aiida_defects/formation_energy/formation_energy_base.py
aiida_defects/formation_energy/formation_energy_qe.py
aiida_defects/formation_energy/formation_energy_siesta.py
aiida_defects/formation_energy/pot_align.py
aiida_defects/formation_energy/utils.py
aiida_defects/formation_energy/chemical_potential/__init__.py
aiida_defects/formation_energy/chemical_potential/chemical_potential.py
aiida_defects/formation_energy/chemical_potential/utils.py
aiida_defects/formation_energy/corrections/__init__.py
aiida_defects/formation_energy/corrections/bandfilling/__init__.py
aiida_defects/formation_energy/corrections/bandfilling/bandfilling.py
aiida_defects/formation_energy/corrections/bandfilling/utils.py
aiida_defects/formation_energy/corrections/gaussian_countercharge/__init__.py
aiida_defects/formation_energy/corrections/gaussian_countercharge/gaussian_countercharge.py
aiida_defects/formation_energy/corrections/gaussian_countercharge/poisson_solver.py.cull
aiida_defects/formation_energy/corrections/gaussian_countercharge/utils.py
aiida_defects/formation_energy/corrections/gaussian_countercharge/model_potential/__init__.py
aiida_defects/formation_energy/corrections/gaussian_countercharge/model_potential/model_potential.py
aiida_defects/formation_energy/corrections/gaussian_countercharge/model_potential/utils.py
aiida_defects/formation_energy/corrections/point_countercharge/__init__.py
aiida_defects/formation_energy/corrections/point_countercharge/point_countercharge.py
aiida_defects/formation_energy/fermi_level/__init__.py
aiida_defects/formation_energy/fermi_level/fermi_level.py
aiida_defects/formation_energy/fermi_level/utils.py
aiida_defects/formation_energy/potential_alignment/__init__.py
aiida_defects-1.0.1.dist-info/entry_points.txt
aiida_defects-1.0.1.dist-info/LICENSE
aiida_defects-1.0.1.dist-info/WHEEL
aiida_defects-1.0.1.dist-info/METADATA
aiida_defects-1.0.1.dist-info/RECORD
