Metadata-Version: 2.1
Name: aiida-defects
Version: 1.0.1
Summary: AiiDA-Defects is a plugin for the AiiDA computational materials science framework, and provides tools and automated workflows for the study of defects in materials.
Keywords: aiida,plugin
Author: The AiiDA-Defects developers
Requires-Python: >=3.8
Classifier: Programming Language :: Python
Classifier: Intended Audience :: Science/Research
Classifier: License :: OSI Approved :: MIT License
Classifier: Natural Language :: English
Classifier: Development Status :: 4 - Beta
Classifier: Framework :: AiiDA
Requires-Dist: aiida-core>=2.0,<3
Requires-Dist: aiida-quantumespresso>=4.2.0
Requires-Dist: pgtest~=1.3.1 ; extra == "testing"
Requires-Dist: wheel~=0.31 ; extra == "testing"
Requires-Dist: pytest~=6.0 ; extra == "testing"
Requires-Dist: pytest-cov ; extra == "testing"
Project-URL: Source, https://github.com/epfl-theos/aiida-defects
Provides-Extra: testing
